pysmartthings/__init__.py
pysmartthings/attribute.py
pysmartthings/capability.py
pysmartthings/command.py
pysmartthings/const.py
pysmartthings/exceptions.py
pysmartthings/models.py
pysmartthings/py.typed
pysmartthings/smartthings.py
pysmartthings-3.5.1.dist-info/METADATA
pysmartthings-3.5.1.dist-info/WHEEL
pysmartthings-3.5.1.dist-info/licenses/LICENSE
pysmartthings-3.5.1.dist-info/RECORD
