Metadata-Version: 2.4
Name: pysmartthings
Version: 3.5.1
Summary: Asynchronous Python client for SmartThings.
License: Apache-2.0
License-File: LICENSE
Keywords: smartthings,api,async,client
Author: Andrew Sayre
Author-email: andrew@sayre.net
Maintainer: Joost Lekkerkerker
Maintainer-email: joostlek@outlook.com
Requires-Python: >=3.12,<4.0
Classifier: Development Status :: 5 - Production/Stable
Classifier: Framework :: AsyncIO
Classifier: Intended Audience :: Developers
Classifier: License :: OSI Approved :: Apache Software License
Classifier: Natural Language :: English
Classifier: Programming Language :: Python :: 3
Classifier: Programming Language :: Python :: 3.12
Classifier: Programming Language :: Python :: 3.13
Classifier: Programming Language :: Python :: 3.14
Classifier: Topic :: Home Automation
Classifier: Topic :: Software Development :: Libraries :: Python Modules
Requires-Dist: aiohttp (>=3.0.0)
Requires-Dist: aiohttp-sse-client2 (>=0.3.0,<0.4.0)
Requires-Dist: mashumaro (>=3.11,<4.0)
Requires-Dist: orjson (>=3.9.10,<4.0.0)
Requires-Dist: yarl (>=1.6.0)
Project-URL: Bug Tracker, https://github.com/pySmartThings/pysmartthings/issues
Project-URL: Changelog, https://github.com/pySmartThings/pysmartthings/releases
Project-URL: Documentation, https://github.com/pySmartThings/pysmartthings
Project-URL: Homepage, https://github.com/pySmartThings/pysmartthings
Project-URL: Repository, https://github.com/pySmartThings/pysmartthings
